Metadata-Version: 1.0
Name: tensorflow-model
Version: 0.1.0
Summary: Command-line tool to inspect TensorFlow models
Home-page: https://github.com/tobegit3hub/tfmodel
Author: tobe
Author-email: tobeg3oogle@gmail.com
License: UNKNOWN
Platform: UNKNOWN
